statatest/README.md
statatest/__init__.py
statatest/__main__.py
statatest/ado/README.md
statatest/ado/assertions/README.md
statatest/ado/assertions/assert_approx_equal.ado
statatest/ado/assertions/assert_count.ado
statatest/ado/assertions/assert_equal.ado
statatest/ado/assertions/assert_error.ado
statatest/ado/assertions/assert_false.ado
statatest/ado/assertions/assert_file_exists.ado
statatest/ado/assertions/assert_identity.ado
statatest/ado/assertions/assert_in_range.ado
statatest/ado/assertions/assert_label_exists.ado
statatest/ado/assertions/assert_no_missing.ado
statatest/ado/assertions/assert_noerror.ado
statatest/ado/assertions/assert_obs_count.ado
statatest/ado/assertions/assert_panel_structure.ado
statatest/ado/assertions/assert_positive.ado
statatest/ado/assertions/assert_sorted.ado
statatest/ado/assertions/assert_sum_equals.ado
statatest/ado/assertions/assert_true.ado
statatest/ado/assertions/assert_unique.ado
statatest/ado/assertions/assert_var_exists.ado
statatest/ado/assertions/assert_var_type.ado
statatest/ado/fixtures/README.md
statatest/ado/fixtures/fixture_balanced_panel.ado
statatest/ado/fixtures/fixture_bipartite_network.ado
statatest/ado/fixtures/fixture_directed_network.ado
statatest/ado/fixtures/fixture_empty_dataset.ado
statatest/ado/fixtures/fixture_multilevel_panel.ado
statatest/ado/fixtures/fixture_seed.ado
statatest/ado/fixtures/fixture_tempfile.ado
statatest/ado/fixtures/fixture_unbalanced_panel.ado
statatest/ado/fixtures/use_fixture.ado
statatest/cli.py
statatest/core/README.md
statatest/core/__init__.py
statatest/core/config.py
statatest/core/constants.py
statatest/core/logging.py
statatest/core/models.py
statatest/coverage/README.md
statatest/coverage/__init__.py
statatest/coverage/aggregator.py
statatest/coverage/instrument.py
statatest/coverage/models.py
statatest/coverage/reporter.py
statatest/discovery/README.md
statatest/discovery/__init__.py
statatest/discovery/finder.py
statatest/discovery/parser.py
statatest-0.1.1.dist-info/WHEEL
statatest-0.1.1.dist-info/entry_points.txt
statatest-0.1.1.dist-info/METADATA
statatest-0.1.1.dist-info/RECORD
