Metadata-Version: 2.4
Name: statatest
Version: 0.1.1
Summary: Pytest-inspired testing and code coverage framework for Stata
Keywords: stata,testing,coverage,pytest,econometrics
Author: Jose Ignacio Gonzalez Rojas
Author-email: Jose Ignacio Gonzalez Rojas <j.i.gonzalez-rojas@lse.ac.uk>
License-Expression: MIT
Classifier: Development Status :: 3 - Alpha
Classifier: Environment :: Console
Classifier: Intended Audience :: Science/Research
Classifier: License :: OSI Approved :: MIT License
Classifier: Operating System :: OS Independent
Classifier: Programming Language :: Python :: 3
Classifier: Programming Language :: Python :: 3.11
Classifier: Programming Language :: Python :: 3.12
Classifier: Programming Language :: Python :: 3.13
Classifier: Topic :: Scientific/Engineering
Classifier: Topic :: Software Development :: Testing
Requires-Dist: click>=8.1.0
Requires-Dist: tomli>=2.0.0 ; python_full_version < '3.11'
Requires-Dist: pytest>=8.0.0 ; extra == 'dev'
Requires-Dist: pytest-cov>=4.0.0 ; extra == 'dev'
Requires-Dist: ruff>=0.1.0 ; extra == 'dev'
Requires-Dist: mypy>=1.0.0 ; extra == 'dev'
Requires-Dist: mkdocs>=1.5.0 ; extra == 'docs'
Requires-Dist: mkdocs-material>=9.5.0 ; extra == 'docs'
Requires-Dist: pymdown-extensions>=10.0.0 ; extra == 'docs'
Requires-Python: >=3.11
Project-URL: Changelog, https://github.com/jigonr/statatest/blob/main/CHANGELOG.md
Project-URL: Documentation, https://jigonzalez.com/statatest/
Project-URL: Homepage, https://github.com/jigonr/statatest
Project-URL: Issues, https://github.com/jigonr/statatest/issues
Project-URL: Repository, https://github.com/jigonr/statatest
Provides-Extra: dev
Provides-Extra: docs
